llama_index/py.typed
llama_index/vector_stores/elasticsearch/__init__.py
llama_index/vector_stores/elasticsearch/base.py
llama_index/vector_stores/elasticsearch/utils.py
llama_index_vector_stores_elasticsearch-0.5.0.dist-info/METADATA
llama_index_vector_stores_elasticsearch-0.5.0.dist-info/WHEEL
llama_index_vector_stores_elasticsearch-0.5.0.dist-info/licenses/LICENSE
llama_index_vector_stores_elasticsearch-0.5.0.dist-info/RECORD
