Metadata-Version: 2.4
Name: llama-index-vector-stores-elasticsearch
Version: 0.5.0
Summary: llama-index vector_stores elasticsearch integration
Author-email: Your Name <you@example.com>
License-Expression: MIT
License-File: LICENSE
Requires-Python: <4.0,>=3.9
Requires-Dist: aiohttp<4,>=3.9.5
Requires-Dist: elasticsearch<9,>=8.13.1
Requires-Dist: llama-index-core<0.14,>=0.13.0
